README.txt
setup.py
HanabIRC.egg-info/PKG-INFO
HanabIRC.egg-info/SOURCES.txt
HanabIRC.egg-info/dependency_links.txt
HanabIRC.egg-info/requires.txt
HanabIRC.egg-info/top_level.txt
bin/hanabIRC
hanabIRC/GameResponse.py
hanabIRC/__init__.py
hanabIRC/game_history.py
hanabIRC/hanabi.py
hanabIRC/hanabot.py
hanabIRC/text_markup.py