Metadata-Version: 1.0
Name: HanabIRC
Version: 1.0.99
Summary: An IRC bot that organizes and plays the card game Hanabi.
Home-page: https://github.com/philsstein/hanabIRC
Author: Phil S. Stein
Author-email: phil.s.stein@gmail.com
License: FreeBSD License
Platform: UNKNOWN
